<anim ver="netanim-3.108" filetype="animation" >
<node id="0" sysId="0" locX="0" locY="10" />
<node id="1" sysId="0" locX="75" locY="41" />
<node id="2" sysId="0" locX="30" locY="24" />
<node id="3" sysId="0" locX="74" locY="33" />
<node id="4" sysId="0" locX="20" locY="94" />
<node id="5" sysId="0" locX="0" locY="0" />
<node id="6" sysId="0" locX="5" locY="0" />
<node id="7" sysId="0" locX="10" locY="0" />
<nu p="c" t="0" id="0" r="255" g="0" b="0" />
<nu p="c" t="0" id="1" r="255" g="0" b="0" />
<nu p="c" t="0" id="2" r="255" g="0" b="0" />
<nu p="c" t="0" id="3" r="255" g="0" b="0" />
<nu p="c" t="0" id="4" r="255" g="0" b="0" />
<nu p="c" t="0" id="5" r="255" g="0" b="0" />
<nu p="c" t="0" id="6" r="255" g="0" b="0" />
<nu p="c" t="0" id="7" r="255" g="0" b="0" />
<link fromId="0" toId="1" fd="10.1.1.1~00:00:00:00:00:01" td="10.1.1.2~00:00:00:00:00:02" ld="" />
<nonp2plinkproperties id="0" ipAddress="10.1.3.4~00:00:00:00:00:0a" channelType="ns3::YansWifiChannel" />
<nonp2plinkproperties id="0" ipAddress="127.0.0.1~00:00:00:00:00:00" channelType="Unknown channel" />
<nonp2plinkproperties id="1" ipAddress="10.1.2.1~00:00:00:00:00:03" channelType="ns3::CsmaChannel" />
<nonp2plinkproperties id="1" ipAddress="127.0.0.1~00:00:00:00:00:00" channelType="Unknown channel" />
<nonp2plinkproperties id="2" ipAddress="10.1.2.2~00:00:00:00:00:04" channelType="ns3::CsmaChannel" />
<nonp2plinkproperties id="2" ipAddress="127.0.0.1~00:00:00:00:00:00" channelType="Unknown channel" />
<nonp2plinkproperties id="3" ipAddress="10.1.2.3~00:00:00:00:00:05" channelType="ns3::CsmaChannel" />
<nonp2plinkproperties id="3" ipAddress="127.0.0.1~00:00:00:00:00:00" channelType="Unknown channel" />
<nonp2plinkproperties id="4" ipAddress="10.1.2.4~00:00:00:00:00:06" channelType="ns3::CsmaChannel" />
<nonp2plinkproperties id="4" ipAddress="127.0.0.1~00:00:00:00:00:00" channelType="Unknown channel" />
<nonp2plinkproperties id="5" ipAddress="10.1.3.1~00:00:00:00:00:07" channelType="ns3::YansWifiChannel" />
<nonp2plinkproperties id="5" ipAddress="127.0.0.1~00:00:00:00:00:00" channelType="Unknown channel" />
<nonp2plinkproperties id="6" ipAddress="10.1.3.2~00:00:00:00:00:08" channelType="ns3::YansWifiChannel" />
<nonp2plinkproperties id="6" ipAddress="127.0.0.1~00:00:00:00:00:00" channelType="Unknown channel" />
<nonp2plinkproperties id="7" ipAddress="10.1.3.3~00:00:00:00:00:09" channelType="ns3::YansWifiChannel" />
<nonp2plinkproperties id="7" ipAddress="127.0.0.1~00:00:00:00:00:00" channelType="Unknown channel" />
<ip n="0" >
<address >10.1.1.1</address>

<address >10.1.3.4</address>

<address >127.0.0.1</address>

</ip>
<ip n="0" >
<address >10.1.1.1</address>

<address >10.1.3.4</address>

<address >127.0.0.1</address>

</ip>
<ip n="0" >
<address >10.1.1.1</address>

<address >10.1.3.4</address>

<address >127.0.0.1</address>

</ip>
<ip n="1" >
<address >10.1.1.2</address>

<address >10.1.2.1</address>

<address >127.0.0.1</address>

</ip>
<ip n="1" >
<address >10.1.1.2</address>

<address >10.1.2.1</address>

<address >127.0.0.1</address>

</ip>
<ip n="1" >
<address >10.1.1.2</address>

<address >10.1.2.1</address>

<address >127.0.0.1</address>

</ip>
<ip n="2" >
<address >10.1.2.2</address>

<address >127.0.0.1</address>

</ip>
<ip n="2" >
<address >10.1.2.2</address>

<address >127.0.0.1</address>

</ip>
<ip n="3" >
<address >10.1.2.3</address>

<address >127.0.0.1</address>

</ip>
<ip n="3" >
<address >10.1.2.3</address>

<address >127.0.0.1</address>

</ip>
<ip n="4" >
<address >10.1.2.4</address>

<address >127.0.0.1</address>

</ip>
<ip n="4" >
<address >10.1.2.4</address>

<address >127.0.0.1</address>

</ip>
<ip n="5" >
<address >10.1.3.1</address>

<address >127.0.0.1</address>

</ip>
<ip n="5" >
<address >10.1.3.1</address>

<address >127.0.0.1</address>

</ip>
<ip n="6" >
<address >10.1.3.2</address>

<address >127.0.0.1</address>

</ip>
<ip n="6" >
<address >10.1.3.2</address>

<address >127.0.0.1</address>

</ip>
<ip n="7" >
<address >10.1.3.3</address>

<address >127.0.0.1</address>

</ip>
<ip n="7" >
<address >10.1.3.3</address>

<address >127.0.0.1</address>

</ip>
<ipv6 n="0" >
<address >::1</address>

</ipv6>
<ipv6 n="1" >
<address >::1</address>

</ipv6>
<ipv6 n="2" >
<address >::1</address>

</ipv6>
<ipv6 n="3" >
<address >::1</address>

</ipv6>
<ipv6 n="4" >
<address >::1</address>

</ipv6>
<ipv6 n="5" >
<address >::1</address>

</ipv6>
<ipv6 n="6" >
<address >::1</address>

</ipv6>
<ipv6 n="7" >
<address >::1</address>

</ipv6>
<nu p="s" t="0" id="0" w="1" h="1" />
<nu p="s" t="0" id="1" w="1" h="1" />
<nu p="s" t="0" id="2" w="1" h="1" />
<nu p="s" t="0" id="3" w="1" h="1" />
<nu p="s" t="0" id="4" w="1" h="1" />
<nu p="s" t="0" id="5" w="1" h="1" />
<nu p="s" t="0" id="6" w="1" h="1" />
<nu p="s" t="0" id="7" w="1" h="1" />
<ncs ncId="0" n="RemainingEnergy" t="DOUBLE" />
<nu p="p" t="0" id="0" x="100" y="100" />
<nu p="p" t="0" id="5" x="0" y="0" />
<nu p="p" t="0" id="6" x="5" y="0" />
<nu p="p" t="0" id="7" x="10" y="0" />
<pr uId="1" fId="0" fbTx="0.03209" />
<pr uId="2" fId="0" fbTx="0.13449" />
<pr uId="3" fId="0" fbTx="0.23689" />
<nu p="p" t="0.25" id="1" x="10" y="10" />
<nu p="p" t="0.25" id="2" x="10" y="30" />
<nu p="p" t="0.25" id="3" x="10" y="50" />
<nu p="p" t="0.25" id="4" x="10" y="70" />
<nu p="p" t="0.25" id="7" x="10.36295971" y="0.8723790085" />
<nu p="p" t="0.256281227" id="5" x="-0.6391702038" y="-0.769065308" />
<nu p="p" t="0.264585837" id="7" x="10.384136" y="0.9232765206" />
<nu p="p" t="0.320948066" id="6" x="4.232407347" y="-0.6409379966" />
<pr uId="4" fId="0" fbTx="0.33929" />
<pr uId="5" fId="0" fbTx="0.44169" />
<nu p="p" t="0.5" id="7" x="10.2928136" y="1.424537656" />
<pr uId="6" fId="0" fbTx="0.54409" />
<nu p="p" t="0.616210239" id="5" x="-0.3765387062" y="0.1958308994" />
<pr uId="7" fId="0" fbTx="0.64649" />
<nu p="p" t="0.726624318" id="7" x="10.20490098" y="1.907082807" />
<nu p="p" t="0.727640319" id="6" x="5.212048279" y="-0.4401803316" />
<pr uId="8" fId="0" fbTx="0.74889" />
<pr uId="9" fId="0" fbTx="0.85129" />
<nu p="p" t="0.906265965" id="5" x="-0.5746742159" y="1.176005534" />
<pr uId="10" fId="0" fbTx="0.95369" />
<nu p="p" t="1" id="6" x="5.085679077" y="0.2503424349" />
<pr uId="11" fId="0" fbTx="1.05609" />
<nu p="p" t="1.115622242" id="6" x="5.032032772" y="0.5434834393" />
<pr uId="12" fId="0" fbTx="1.15849" />
<nu p="p" t="1.21726661" id="7" x="10.81359727" y="1.113679488" />
<nu p="p" t="1.25" id="5" x="-1.411652135" y="0.8720066798" />
<pr uId="13" fId="0" fbTx="1.26089" />
<nu p="p" t="1.292277571" id="5" x="-1.514596242" y="0.8346163377" />
<pr uId="14" fId="0" fbTx="1.36329" />
<nu p="p" t="1.373556785" id="6" x="5.119255272" y="-0.4527054136" />
<pr uId="15" fId="0" fbTx="1.46569" />
<nu p="p" t="1.5" id="5" x="-1.912078012" y="1.248168974" />
<nu p="p" t="1.5" id="6" x="4.845121921" y="-0.05197964925" />
<nu p="p" t="1.553912411" id="7" x="10.84516282" y="2.113181172" />
<pr uId="16" fId="0" fbTx="1.56809" />
<nu p="p" t="1.633984912" id="6" x="4.554637905" y="0.3726473762" />
<nu p="p" t="1.654415377" id="5" x="-2.20755548" y="1.555593101" />
<pr uId="17" fId="0" fbTx="1.67049" />
<pr uId="18" fId="0" fbTx="1.77289" />
<pr uId="19" fId="0" fbTx="1.87529" />
<nu p="p" t="1.905858773" id="7" x="10.9796972" y="3.104090098" />
<nu p="p" t="1.948683891" id="5" x="-2.144543421" y="2.553605866" />
<pr uId="20" fId="0" fbTx="1.97769" />
<nu p="p" t="1.982248959" id="6" x="3.862261533" y="1.0941839" />
<nu p="p" t="2" id="7" x="11.08431876" y="3.386347858" />
<pr uId="21" fId="0" fbTx="2.08009" />
<pr uId="22" fId="0" fbTx="2.18249" />
<nu p="p" t="2.218595966" id="7" x="11.32725006" y="4.041750488" />
<nu p="p" t="2.25" id="5" x="-1.380575338" y="2.125327209" />
<nu p="p" t="2.25" id="6" x="3.924966102" y="0.4921178403" />
<pr uId="23" fId="0" fbTx="2.28489" />
<nu p="p" t="2.292720689" id="5" x="-1.272259713" y="2.064605731" />
<pr uId="24" fId="0" fbTx="2.38729" />
<nu p="p" t="2.424576831" id="6" x="3.965850219" y="0.09956368093" />
<pr uId="25" fId="0" fbTx="2.48969" />
<nu p="p" t="2.5" id="5" x="-0.9297426936" y="2.319892578" />
<nu p="p" t="2.5" id="6" x="4.229263956" y="0.2185855473" />
<pr uId="26" fId="0" fbTx="2.59209" />
<nu p="p" t="2.6398409" id="7" x="12.01303808" y="4.769551827" />
<nu p="p" t="2.68550667" id="6" x="4.877141867" y="0.5113251705" />
<pr uId="27" fId="0" fbTx="2.69449" />
<nu p="p" t="2.75" id="7" x="12.15849313" y="5.085099451" />
<nu p="p" t="2.777939103" id="5" x="-0.4704644734" y="2.662204586" />
<pr uId="28" fId="0" fbTx="2.79689" />
<pr uId="29" fId="0" fbTx="2.89929" />
<nu p="p" t="2.940587483" id="6" x="3.896594991" y="0.3150401277" />
<nu p="p" t="2.95688328" id="7" x="12.43166364" y="5.677710753" />
<nu p="p" t="3" id="5" x="0.06452634565" y="2.723834341" />
<pr uId="30" fId="0" fbTx="3.00169" />
<pr uId="31" fId="0" fbTx="3.10409" />
<nu p="p" t="3.190286307" id="5" x="0.5229655784" y="2.776645524" />
<pr uId="32" fId="0" fbTx="3.20649" />
<nu p="p" t="3.220474737" id="7" x="11.46066931" y="5.916813252" />
<nu p="p" t="3.25" id="6" x="4.289576349" y="-0.3303166248" />
<pr uId="33" fId="0" fbTx="3.30889" />
<nu p="p" t="3.350084148" id="6" x="4.4166921" y="-0.5390670056" />
<pr uId="34" fId="0" fbTx="3.41129" />
<nu p="p" t="3.45725936" id="5" x="0.7053642107" y="3.759870186" />
<nu p="p" t="3.5" id="7" x="11.9324137" y="6.624204614" />
<pr uId="35" fId="0" fbTx="3.51369" />
<nu p="p" t="3.54922669" id="7" x="12.01549176" y="6.748782032" />
<nu p="p" t="3.614987269" id="6" x="4.831030595" y="0.3710558459" />
<pr uId="36" fId="0" fbTx="3.61609" />
<pr uId="37" fId="0" fbTx="3.71849" />
<pr uId="38" fId="0" fbTx="3.82089" />
<nu p="p" t="3.871165417" id="5" x="0.1429612034" y="2.933006924" />
<nu p="p" t="3.873990049" id="6" x="3.93957453" y="0.824162985" />
<nu p="p" t="3.878337337" id="7" x="13.00759544" y="6.623361661" />
<pr uId="39" fId="0" fbTx="3.92329" />
<nu p="p" t="4" id="7" x="12.83267412" y="6.196380454" />
<pr uId="40" fId="0" fbTx="4.02569" />
<nu p="p" t="4.123770512" id="5" x="0.2355241295" y="1.937300088" />
<pr uId="41" fId="0" fbTx="4.12809" />
<nu p="p" t="4.142006208" id="7" x="12.62850373" y="5.698002557" />
<pr uId="42" fId="0" fbTx="4.23049" />
<nu p="p" t="4.329372595" id="6" x="3.801015206" y="-0.1661911484" />
<pr uId="43" fId="0" fbTx="4.33289" />
<nu p="p" t="4.37676813" id="5" x="1.215150659" y="1.736472155" />
<pr uId="44" fId="0" fbTx="4.43529" />
<nu p="p" t="4.5" id="5" x="0.9652452639" y="1.790729621" />
<nu p="p" t="4.5" id="7" x="13.30872751" y="4.987327881" />
<nu p="p" t="4.505913715" id="7" x="13.31996415" y="4.975588215" />
<pr uId="45" fId="0" fbTx="4.53769" />
<pr uId="46" fId="0" fbTx="4.64009" />
<nu p="p" t="4.674853082" id="6" x="3.181035696" y="-0.9508091471" />
<pr uId="47" fId="0" fbTx="4.74249" />
<nu p="p" t="4.75" id="6" x="3.411568775" y="-1.141691053" />
<nu p="p" t="4.797621875" id="7" x="13.11341262" y="3.997152494" />
<pr uId="48" fId="0" fbTx="4.84489" />
<nu p="p" t="4.858655476" id="5" x="0.2379176781" y="1.948641186" />
<nu p="p" t="4.925927373" id="6" x="3.951272598" y="-1.588567028" />
<pr uId="49" fId="0" fbTx="4.94729" />
<nu p="p" t="5" id="7" x="13.42425383" y="4.29459292" />
<pr uId="50" fId="0" fbTx="5.04969" />
<pr uId="51" fId="0" fbTx="5.15209" />
<nu p="p" t="5.166945254" id="5" x="0.4491218265" y="0.971199217" />
<nu p="p" t="5.180243017" id="6" x="3.647774376" y="-0.6357350266" />
<nu p="p" t="5.25" id="5" x="0.2337413189" y="1.08214528" />
<pr uId="52" fId="0" fbTx="5.25449" />
<nu p="p" t="5.26802316" id="7" x="13.83592204" y="4.688513573" />
<pr uId="53" fId="0" fbTx="5.35689" />
<nu p="p" t="5.441593461" id="6" x="3.661698584" y="-1.635638077" />
<pr uId="54" fId="0" fbTx="5.45929" />
<nu p="p" t="5.5" id="5" x="-0.4145675314" y="1.416099895" />
<nu p="p" t="5.5" id="7" x="13.64169735" y="3.904983889" />
<nu p="p" t="5.509755325" id="5" x="-0.4398653855" y="1.429131238" />
<nu p="p" t="5.555392278" id="7" x="13.59531967" y="3.717889806" />
<pr uId="55" fId="0" fbTx="5.56169" />
<pr uId="56" fId="0" fbTx="5.66409" />
<nu p="p" t="5.729710121" id="6" x="3.734169049" y="-2.633008633" />
<nu p="p" t="5.75" id="7" x="13.12303659" y="4.028091761" />
<pr uId="57" fId="0" fbTx="5.76649" />
<pr uId="58" fId="0" fbTx="5.86889" />
<nu p="p" t="5.899802909" id="7" x="12.75948791" y="4.266875479" />
<nu p="p" t="5.924449291" id="5" x="-0.8839267823" y="2.325127596" />
<pr uId="59" fId="0" fbTx="5.97129" />
<nu p="p" t="6" id="5" x="-1.094378663" y="2.220594235" />
<nu p="p" t="6" id="6" x="3.907013827" y="-3.430418531" />
<nu p="p" t="6.060977106" id="6" x="3.946007423" y="-3.610313346" />
<pr uId="60" fId="0" fbTx="6.07369" />
<pr uId="61" fId="0" fbTx="6.17609" />
<nu p="p" t="6.245964324" id="5" x="-1.779529807" y="1.88027344" />
<nu p="p" t="6.25" id="7" x="11.94982577" y="4.333704235" />
<pr uId="62" fId="0" fbTx="6.27849" />
<nu p="p" t="6.330859572" id="7" x="11.76287695" y="4.349134817" />
<nu p="p" t="6.378695905" id="6" x="3.411788809" y="-2.764966984" />
<pr uId="63" fId="0" fbTx="6.38089" />
<pr uId="64" fId="0" fbTx="6.48329" />
<nu p="p" t="6.498566687" id="5" x="-1.208511913" y="1.059335828" />
<nu p="p" t="6.5" id="6" x="2.987140908" y="-2.751039827" />
<pr uId="65" fId="0" fbTx="6.58569" />
<nu p="p" t="6.656187619" id="7" x="11.22924714" y="5.194852984" />
<nu p="p" t="6.664200455" id="6" x="2.412326196" y="-2.732187656" />
<pr uId="66" fId="0" fbTx="6.68809" />
<nu p="p" t="6.75" id="5" x="-0.8587186692" y="0.6172180958" />
<nu p="p" t="6.75" id="7" x="10.86293274" y="5.157697198" />
<pr uId="67" fId="0" fbTx="6.79049" />
<pr uId="68" fId="0" fbTx="6.89289" />
<nu p="p" t="6.910978273" id="7" x="10.23435195" y="5.093939364" />
<nu p="p" t="6.944561575" id="5" x="-0.5880452103" y="0.2751030381" />
<pr uId="69" fId="0" fbTx="6.99529" />
<nu p="p" t="7" id="6" x="1.82655546" y="-3.484600651" />
<nu p="p" t="7" id="7" x="10.01281435" y="4.970916755" />
<nu p="p" t="7.016358659" id="6" x="1.798019317" y="-3.521254863" />
<pr uId="70" fId="0" fbTx="7.09769" />
<pr uId="71" fId="0" fbTx="7.20009" />
<nu p="p" t="7.224577507" id="5" x="-0.1663122707" y="-0.6316170521" />
<nu p="p" t="7.25" id="6" x="2.238799513" y="-4.168679363" />
<nu p="p" t="7.25" id="7" x="9.390669608" y="4.62543197" />
<nu p="p" t="7.262282152" id="7" x="9.360104503" y="4.608458784" />
<pr uId="72" fId="0" fbTx="7.30249" />
<nu p="p" t="7.314664419" id="6" x="2.360793314" y="-4.347865671" />
<pr uId="73" fId="0" fbTx="7.40489" />
<nu p="p" t="7.5" id="5" x="-0.7974957934" y="0.04617955985" />
<nu p="p" t="7.5" id="6" x="1.788368352" y="-4.701614729" />
<nu p="p" t="7.5" id="7" x="8.715054633" y="4.419946368" />
<pr uId="74" fId="0" fbTx="7.50729" />
<nu p="p" t="7.521953674" id="5" x="-0.8478068524" y="0.1002061054" />
<nu p="p" t="7.590088181" id="6" x="1.510123218" y="-4.873565571" />
<pr uId="75" fId="0" fbTx="7.60969" />
<nu p="p" t="7.616012396" id="7" x="8.400253782" y="4.327947483" />
<pr uId="76" fId="0" fbTx="7.71209" />
<nu p="p" t="7.75" id="5" x="-1.507558523" y="0.5520571418" />
<nu p="p" t="7.75" id="6" x="1.228469077" y="-5.044511824" />
<nu p="p" t="7.807136013" id="5" x="-1.672856428" y="0.6652664496" />
<pr uId="77" fId="0" fbTx="7.81449" />
<nu p="p" t="7.897975823" id="7" x="9.142921407" y="4.997607693" />
<pr uId="78" fId="0" fbTx="7.91689" />
<nu p="p" t="8" id="5" x="-2.06386939" y="0.4368425898" />
<nu p="p" t="8" id="6" x="0.7881418041" y="-5.311762634" />
<nu p="p" t="8" id="7" x="9.128890628" y="5.231319195" />
<pr uId="79" fId="0" fbTx="8.01929" />
<nu p="p" t="8.075446296" id="6" x="0.6552575569" y="-5.392414968" />
<pr uId="80" fId="0" fbTx="8.12169" />
<pr uId="81" fId="0" fbTx="8.22409" />
<nu p="p" t="8.233030052" id="5" x="-2.536315138" y="0.1608469271" />
<pr uId="82" fId="0" fbTx="8.32649" />
<nu p="p" t="8.333730229" id="7" x="9.082994691" y="5.99581047" />
<nu p="p" t="8.39136577" id="6" x="0.2607334667" y="-6.311300565" />
<pr uId="83" fId="0" fbTx="8.42889" />
<nu p="p" t="8.5" id="5" x="-2.57205511" y="-0.4363337148" />
<nu p="p" t="8.5" id="6" x="-0.0794492684" y="-6.213310971" />
<nu p="p" t="8.5" id="7" x="8.536801191" y="5.617844026" />
<pr uId="84" fId="0" fbTx="8.53129" />
<nu p="p" t="8.584054206" id="7" x="8.260684489" y="5.426770993" />
<pr uId="85" fId="0" fbTx="8.63369" />
<nu p="p" t="8.679282154" id="5" x="-2.596056085" y="-0.837366987" />
<nu p="p" t="8.698229571" id="6" x="-0.7001953964" y="-6.034505127" />
<pr uId="86" fId="0" fbTx="8.73609" />
<nu p="p" t="8.75" id="5" x="-2.688445147" y="-1.02764187" />
<nu p="p" t="8.75" id="6" x="-0.7637030776" y="-5.881832677" />
<pr uId="87" fId="0" fbTx="8.83849" />
<pr uId="88" fId="0" fbTx="8.94089" />
<nu p="p" t="9" id="5" x="-3.015056701" y="-1.700296986" />
<nu p="p" t="9" id="6" x="-1.070382404" y="-5.144575648" />
<nu p="p" t="9" id="7" x="8.350652134" y="6.33588112" />
<nu p="p" t="9.011317128" id="6" x="-1.084265321" y="-5.11120112" />
<nu p="p" t="9.013615521" id="5" x="-3.032844647" y="-1.736931185" />
<nu p="p" t="9.039360807" id="7" x="8.359165741" y="6.421909897" />
<pr uId="89" fId="0" fbTx="9.04329" />
<pr uId="90" fId="0" fbTx="9.14569" />
<pr uId="91" fId="0" fbTx="9.24809" />
<nu p="p" t="9.25" id="5" x="-2.628048081" y="-2.205831739" />
<nu p="p" t="9.25" id="6" x="-0.3769793724" y="-5.270533722" />
<nu p="p" t="9.25" id="7" x="7.805052466" y="7.001383498" />
<nu p="p" t="9.302079343" id="7" x="7.668051109" y="7.144655051" />
<nu p="p" t="9.340530093" id="6" x="-0.108712688" y="-5.330967029" />
<pr uId="92" fId="0" fbTx="9.35049" />
<nu p="p" t="9.395214512" id="5" x="-2.379375512" y="-2.493884345" />
<pr uId="93" fId="0" fbTx="9.45289" />
<nu p="p" t="9.5" id="7" x="7.072571434" y="6.957318558" />
<pr uId="94" fId="0" fbTx="9.55529" />
<nu p="p" t="9.619131661" id="7" x="6.714142537" y="6.844557677" />
<pr uId="95" fId="0" fbTx="9.65769" />
<nu p="p" t="9.726034091" id="6" x="-0.2961863634" y="-6.313236656" />
<nu p="p" t="9.75" id="5" x="-2.026524208" y="-1.627810032" />
<nu p="p" t="9.75" id="7" x="6.577109368" y="7.298061138" />
<pr uId="96" fId="0" fbTx="9.76009" />
<nu p="p" t="9.774585313" id="5" x="-2.002072927" y="-1.567794308" />
<pr uId="97" fId="0" fbTx="9.86249" />
<nu p="p" t="9.895368181" id="7" x="6.42489331" y="7.801811501" />
<pr uId="98" fId="0" fbTx="9.96489" />
</anim>
